HyFetch_testing-1.5.0rc3.data/scripts/neowofetch
hyfetch/__init__.py
hyfetch/color_scale.py
hyfetch/color_util.py
hyfetch/constants.py
hyfetch/main.py
hyfetch/models.py
hyfetch/neofetch_util.py
hyfetch/presets.py
hyfetch/serializer.py
hyfetch/scripts/neowofetch
HyFetch_testing-1.5.0rc3.dist-info/LICENSE.md
HyFetch_testing-1.5.0rc3.dist-info/METADATA
HyFetch_testing-1.5.0rc3.dist-info/WHEEL
HyFetch_testing-1.5.0rc3.dist-info/entry_points.txt
HyFetch_testing-1.5.0rc3.dist-info/top_level.txt
HyFetch_testing-1.5.0rc3.dist-info/RECORD
