Metadata-Version: 2.1
Name: HyFetch-testing
Version: 1.5.0rc3
Summary: neofetch with flags <3
Home-page: https://github.com/hykilpikonna/HyFetch
Author: Azalea Gui
Author-email: me@hydev.org
License: MIT
Platform: UNKNOWN
Classifier: License :: OSI Approved :: MIT License
Classifier: Programming Language :: Python :: 3
Classifier: Programming Language :: Python :: 3.7
Classifier: Programming Language :: Python :: 3.8
Classifier: Programming Language :: Python :: 3.9
Classifier: Programming Language :: Python :: 3.10
Requires-Dist: setuptools
Requires-Dist: typing-extensions
